netblow/__init__.py
netblow/exceptions.py
netblow/netblow.py
netblow/utils.py
netblow/version.py
netblow/bin/__init__.py
netblow/bin/netblow_cli.py
netblow/monkey_patch/__init__.py
netblow/monkey_patch/eos_driver.py
netblow/monkey_patch/ios_driver.py
netblow/monkey_patch/iosxr_driver.py
netblow/monkey_patch/junos_driver.py
netblow-0.1.4.dist-info/LICENSE
netblow-0.1.4.dist-info/METADATA
netblow-0.1.4.dist-info/WHEEL
netblow-0.1.4.dist-info/entry_points.txt
netblow-0.1.4.dist-info/top_level.txt
netblow-0.1.4.dist-info/RECORD
