Metadata-Version: 2.1
Name: netblow
Version: 0.1.4
Summary: Vendor agnostic network testing framework to stress network failures
Home-page: http://github.com/viniciusarcanjo/netblow
Author: Vinicius Arcanjo
Author-email: viniciusarcanjov@gmail.com
License: Apache
Keywords: network testing netblow napalm eos junos ios iosxr
Platform: UNKNOWN
Classifier: Topic :: Utilities
Classifier: Programming Language :: Python
Classifier: Programming Language :: Python :: 3
Classifier: Programming Language :: Python :: 3.4
Classifier: Programming Language :: Python :: 3.5
Classifier: Programming Language :: Python :: 3.6
Classifier: Programming Language :: Python :: 3.7
Classifier: Operating System :: POSIX :: Linux
Classifier: Operating System :: MacOS
Requires-Dist: napalm (==2.3.1)
Requires-Dist: coloredlogs
